procrastinate/__init__.py
procrastinate/__main__.py
procrastinate/app.py
procrastinate/blueprints.py
procrastinate/builtin_tasks.py
procrastinate/cli.py
procrastinate/connector.py
procrastinate/exceptions.py
procrastinate/job_context.py
procrastinate/jobs.py
procrastinate/manager.py
procrastinate/metadata.py
procrastinate/periodic.py
procrastinate/psycopg_connector.py
procrastinate/py.typed
procrastinate/retry.py
procrastinate/schema.py
procrastinate/shell.py
procrastinate/signals.py
procrastinate/sync_psycopg_connector.py
procrastinate/tasks.py
procrastinate/testing.py
procrastinate/types.py
procrastinate/utils.py
procrastinate/worker.py
procrastinate/contrib/README.md
procrastinate/contrib/__init__.py
procrastinate/contrib/aiopg/__init__.py
procrastinate/contrib/aiopg/aiopg_connector.py
procrastinate/contrib/django/README.md
procrastinate/contrib/django/__init__.py
procrastinate/contrib/django/admin.py
procrastinate/contrib/django/apps.py
procrastinate/contrib/django/django_connector.py
procrastinate/contrib/django/exceptions.py
procrastinate/contrib/django/healthchecks.py
procrastinate/contrib/django/migrations_utils.py
procrastinate/contrib/django/models.py
procrastinate/contrib/django/procrastinate_app.py
procrastinate/contrib/django/settings.py
procrastinate/contrib/django/utils.py
procrastinate/contrib/django/management/__init__.py
procrastinate/contrib/django/management/commands/__init__.py
procrastinate/contrib/django/management/commands/procrastinate.py
procrastinate/contrib/django/migrations/0001_initial.py
procrastinate/contrib/django/migrations/0002_drop_started_at_column.py
procrastinate/contrib/django/migrations/0003_drop_started_at_column.py
procrastinate/contrib/django/migrations/0004_drop_procrastinate_version_table.py
procrastinate/contrib/django/migrations/0005_fix_procrastinate_fetch_job.py
procrastinate/contrib/django/migrations/0006_fix_trigger_status_events_insert.py
procrastinate/contrib/django/migrations/0007_add_queueing_lock_column.py
procrastinate-3.6.0.dist-info/METADATA
procrastinate-3.6.0.dist-info/WHEEL
procrastinate-3.6.0.dist-info/entry_points.txt
procrastinate-3.6.0.dist-info/licenses/LICENSE.md
procrastinate-3.6.0.dist-info/RECORD
