Metadata-Version: 2.4
Name: procrastinate
Version: 3.6.0
Summary: Postgres-based distributed task processing library
Project-URL: homepage, https://procrastinate.readthedocs.io/
Project-URL: source, https://github.com/procrastinate-org/procrastinate/
Project-URL: documentation, https://procrastinate.readthedocs.io/
Project-URL: issues, https://github.com/procrastinate-org/procrastinate/issues
Project-URL: changelog, https://github.com/procrastinate-org/procrastinate/releases
Author: Eric Lemoine, Kai Schlamp
Author-email: Joachim Jablon <ewjoachim@gmail.com>
License-File: LICENSE.md
Keywords: postgres,task-queue
Classifier: Development Status :: 4 - Beta
Classifier: Intended Audience :: Developers
Classifier: License :: OSI Approved :: MIT License
Requires-Python: >=3.9
Requires-Dist: asgiref
Requires-Dist: attrs
Requires-Dist: contextlib2; python_version < '3.10'
Requires-Dist: croniter
Requires-Dist: psycopg[pool]
Requires-Dist: python-dateutil
Requires-Dist: typing-extensions
Provides-Extra: aiopg
Requires-Dist: aiopg; extra == 'aiopg'
Requires-Dist: psycopg2-binary; extra == 'aiopg'
Provides-Extra: django
Requires-Dist: django>=2.2; extra == 'django'
Provides-Extra: psycopg2
Requires-Dist: psycopg2-binary; extra == 'psycopg2'
Provides-Extra: sphinx
Requires-Dist: sphinx; extra == 'sphinx'
Provides-Extra: sqlalchemy
Requires-Dist: sqlalchemy~=2.0; extra == 'sqlalchemy'
